gen_data_model/__init__.py
gen_data_model/py.typed
gen_data_model/conf/gen_data_model.cfg
gen_data_model/conf/gen_data_model.logo
gen_data_model/conf/gen_data_model_util.cfg
gen_data_model/conf/model_types.yaml
gen_data_model/conf/template/django.template
gen_data_model/conf/template/django_base_model.template
gen_data_model/conf/template/flask.template
gen_data_model/conf/template/flask_base_model.template
gen_data_model/conf/template/sqlalchemy.template
gen_data_model/conf/template/sqlalchemy_base_model.template
gen_data_model/log/gen_data_model.log
gen_data_model/pro/__init__.py
gen_data_model/pro/read_template.py
gen_data_model/pro/write_template.py
usr/local/bin/gen_data_model_run.py
gen_data_model-2.3.6.dist-info/LICENSE
gen_data_model-2.3.6.dist-info/METADATA
gen_data_model-2.3.6.dist-info/WHEEL
gen_data_model-2.3.6.dist-info/top_level.txt
gen_data_model-2.3.6.dist-info/RECORD
